mess_server_jim-0.0.1.data/scripts/server_run
server/__init__.py
server/server.py
server/common/__init__.py
server/common/decorators.py
server/common/descriptors.py
server/common/errors.py
server/common/metaclasses.py
server/common/utils.py
server/common/variables.py
server/logs/__init__.py
server/logs/client_log_config.py
server/logs/server_log_config.py
server/server/__init__.py
server/server/add_user.py
server/server/base.py
server/server/config_window.py
server/server/main_window.py
server/server/remove_user.py
server/server/server_db.py
server/server/stat_window.py
server/unit_tests/__init__.py
mess_server_jim-0.0.1.dist-info/METADATA
mess_server_jim-0.0.1.dist-info/WHEEL
mess_server_jim-0.0.1.dist-info/top_level.txt
mess_server_jim-0.0.1.dist-info/RECORD
