Metadata-Version: 2.1
Name: mess-server-jim
Version: 0.0.1
Summary: Mess Server
Home-page: UNKNOWN
Author: AlisaEAS
Author-email: alisa.eas@yandex.ru
License: UNKNOWN
Platform: UNKNOWN
Requires-Dist: PyQt5
Requires-Dist: sqlalchemy
Requires-Dist: pycryptodome
Requires-Dist: pycryptodomex
